[
  {
    "ticker": "BKNG",
    "name": "Booking Holdings",
    "exchange": "NASDAQ",
    "lastPrice": 175.72,
    "lastDate": "2026-06-16",
    "avg30": 163.7257,
    "avg90": 169.8583,
    "chgPct": 0.6184,
    "history": [
      {
        "date": "2026-05-05",
        "close": 167.63
      },
      {
        "date": "2026-05-06",
        "close": 168.32
      },
      {
        "date": "2026-05-07",
        "close": 171.28
      },
      {
        "date": "2026-05-08",
        "close": 165.93
      },
      {
        "date": "2026-05-11",
        "close": 157.8
      },
      {
        "date": "2026-05-12",
        "close": 160.56
      },
      {
        "date": "2026-05-13",
        "close": 155.03
      },
      {
        "date": "2026-05-14",
        "close": 154.48
      },
      {
        "date": "2026-05-15",
        "close": 154.13
      },
      {
        "date": "2026-05-18",
        "close": 155.07
      },
      {
        "date": "2026-05-19",
        "close": 154.54
      },
      {
        "date": "2026-05-20",
        "close": 156.95
      },
      {
        "date": "2026-05-21",
        "close": 159.68
      },
      {
        "date": "2026-05-22",
        "close": 161.06
      },
      {
        "date": "2026-05-26",
        "close": 163.3
      },
      {
        "date": "2026-05-27",
        "close": 168.37
      },
      {
        "date": "2026-05-28",
        "close": 169.82
      },
      {
        "date": "2026-05-29",
        "close": 167.43
      },
      {
        "date": "2026-06-01",
        "close": 169.25
      },
      {
        "date": "2026-06-02",
        "close": 167.21
      },
      {
        "date": "2026-06-03",
        "close": 164.78
      },
      {
        "date": "2026-06-04",
        "close": 167.49
      },
      {
        "date": "2026-06-05",
        "close": 165.84
      },
      {
        "date": "2026-06-08",
        "close": 162.3
      },
      {
        "date": "2026-06-09",
        "close": 163.99
      },
      {
        "date": "2026-06-10",
        "close": 160.64
      },
      {
        "date": "2026-06-11",
        "close": 163.59
      },
      {
        "date": "2026-06-12",
        "close": 164.94
      },
      {
        "date": "2026-06-15",
        "close": 174.64
      },
      {
        "date": "2026-06-16",
        "close": 175.72
      }
    ]
  }]